edx_api/__init__.py
edx_api/bulk_user_retirement.py
edx_api/ccx.py
edx_api/ccx_test.py
edx_api/client.py
edx_api/client_test.py
edx_api/constants.py
edx_api/email_settings.py
edx_api/email_settings_test.py
edx_api/integration_test.py
edx_api/certificates/__init__.py
edx_api/certificates/models.py
edx_api/certificates/models_test.py
edx_api/certificates/fixtures/certificates.json
edx_api/course_detail/__init__.py
edx_api/course_detail/init_test.py
edx_api/course_detail/models.py
edx_api/course_detail/models_test.py
edx_api/course_detail/fixtures/course_detail.json
edx_api/course_detail/fixtures/course_mode.json
edx_api/course_list/README.md
edx_api/course_list/__init__.py
edx_api/course_list/constants.py
edx_api/course_list/test_course_list.py
edx_api/course_list/fixtures/course_list_empty.json
edx_api/course_list/fixtures/course_list_page1.json
edx_api/course_list/fixtures/course_list_page2.json
edx_api/course_list/fixtures/course_list_response.json
edx_api/course_runs/__init__.py
edx_api/course_runs/exceptions.py
edx_api/course_runs/init_test.py
edx_api/course_runs/models.py
edx_api/course_runs/models_test.py
edx_api/course_runs/fixtures/course_run.json
edx_api/course_runs/fixtures/course_run_list.json
edx_api/course_structure/__init__.py
edx_api/course_structure/models.py
edx_api/course_structure/models_test.py
edx_api/course_structure/fixtures/course_structure.json
edx_api/enrollments/__init__.py
edx_api/enrollments/init_test.py
edx_api/enrollments/models.py
edx_api/enrollments/models_test.py
edx_api/enrollments/fixtures/enrollments_list.json
edx_api/enrollments/fixtures/user_enrollments.json
edx_api/fixtures/ccx_create_response.json
edx_api/grades/__init__.py
edx_api/grades/init_test.py
edx_api/grades/models.py
edx_api/grades/models_test.py
edx_api/grades/fixtures/course_grades_hawthorn.json
edx_api/grades/fixtures/course_grades_ironwood_p1.json
edx_api/grades/fixtures/course_grades_ironwood_p2.json
edx_api/grades/fixtures/current_grades.json
edx_api_client-1.13.0.dist-info/licenses/LICENSE
edx_api_client-1.13.0.dist-info/METADATA
edx_api_client-1.13.0.dist-info/WHEEL
edx_api_client-1.13.0.dist-info/top_level.txt
edx_api_client-1.13.0.dist-info/RECORD
