Metadata-Version: 2.4
Name: edx-api-client
Version: 1.13.0
Summary: Python interface to the edX REST APIs
Home-page: https://github.com/mitodl/edx-api-client
Author: MIT Office of Digital Learning
Author-email: mitx-devops@mit.edu
License: The AGPL License
Keywords: edx,rest api
Platform: OS Independent
License-File: LICENSE
Requires-Dist: python-dateutil<4.0.0,>=2.5.3
Requires-Dist: requests>=2.20.0
Provides-Extra: dev
Requires-Dist: flake8; extra == "dev"
Dynamic: author
Dynamic: author-email
Dynamic: home-page
Dynamic: keywords
Dynamic: license
Dynamic: license-file
Dynamic: platform
Dynamic: provides-extra
Dynamic: requires-dist
Dynamic: summary
